pyfundamentals/__init__.py
pyfundamentals/basics.py
pyfundamentals/functions.py
pyfundamentals/loops.py
pyfundamentals-0.1.0.dist-info/licenses/LICENSE
pyfundamentals-0.1.0.dist-info/METADATA
pyfundamentals-0.1.0.dist-info/WHEEL
pyfundamentals-0.1.0.dist-info/top_level.txt
pyfundamentals-0.1.0.dist-info/RECORD
