Metadata-Version: 2.4
Name: pyfundamentals
Version: 0.1.0
Summary: A simple package to explain Python fundamentals.
Author-email: Manakavoo <sivabalajimanakavoo@gmail.com>
License: MIT
Project-URL: Homepage, https://github.com/Manakavoo
Classifier: Programming Language :: Python :: 3
Classifier: Topic :: Education
Classifier: License :: OSI Approved :: MIT License
Requires-Python: >=3.8
License-File: LICENSE
Dynamic: license-file
